{
    "option": {
        "伦敦": {
            "type": "select",
            "label": "关卡",
            "default": "旧街",
            "cases": [
                {
                    "name": "旧街",
                    "label": "旧街",
                    "pipeline_override": {
                        "地图坐标导航": {
                            "attach": {
                                "quests": "q变动坐标点0号"
                            }
                        },
                        "关卡选择": {
                            "template": [
                                "map/Fuyuki/熊熊燃烧的森林.png"
                            ]
                        }
                    }
                },
                {
                    "name": "白色教堂",
                    "label": "白色教堂",
                    "pipeline_override": {
                        "地图坐标导航": {
                            "attach": {
                                "quests": "q变动坐标点0号"
                            }
                        },
                        "关卡选择": {
                            "template": [
                                "map/Fuyuki/熊熊燃烧的森林.png"
                            ]
                        }
                    }
                },
                {
                    "name": "伦敦城",
                    "label": "伦敦城",
                    "pipeline_override": {
                        "地图坐标导航": {
                            "attach": {
                                "quests": "q变动坐标点0号"
                            }
                        },
                        "关卡选择": {
                            "template": [
                                "map/Fuyuki/熊熊燃烧的森林.png"
                            ]
                        }
                    }
                },
                {
                    "name": "苏活区",
                    "label": "苏活区",
                    "pipeline_override": {
                        "地图坐标导航": {
                            "attach": {
                                "quests": "q变动坐标点0号"
                            }
                        },
                        "关卡选择": {
                            "template": [
                                "map/Fuyuki/熊熊燃烧的森林.png"
                            ]
                        }
                    }
                },
                {
                    "name": "威斯敏斯特",
                    "label": "威斯敏斯特",
                    "pipeline_override": {
                        "地图坐标导航": {
                            "attach": {
                                "quests": "q变动坐标点0号"
                            }
                        },
                        "关卡选择": {
                            "template": [
                                "map/Fuyuki/熊熊燃烧的森林.png"
                            ]
                        }
                    }
                },
                {
                    "name": "摄政公园",
                    "label": "摄政公园",
                    "pipeline_override": {
                        "地图坐标导航": {
                            "attach": {
                                "quests": "q变动坐标点0号"
                            }
                        },
                        "关卡选择": {
                            "template": [
                                "map/Fuyuki/熊熊燃烧的森林.png"
                            ]
                        }
                    }
                },
                {
                    "name": "克勒肯维尔",
                    "label": "克勒肯维尔",
                    "pipeline_override": {
                        "地图坐标导航": {
                            "attach": {
                                "quests": "q变动坐标点0号"
                            }
                        },
                        "关卡选择": {
                            "template": [
                                "map/Fuyuki/熊熊燃烧的森林.png"
                            ]
                        }
                    }
                },
                {
                    "name": "萨瑟克",
                    "label": "萨瑟克",
                    "pipeline_override": {
                        "地图坐标导航": {
                            "attach": {
                                "quests": "q变动坐标点0号"
                            }
                        },
                        "关卡选择": {
                            "template": [
                                "map/Fuyuki/熊熊燃烧的森林.png"
                            ]
                        }
                    }
                },
                {
                    "name": "海德公园",
                    "label": "海德公园",
                    "pipeline_override": {
                        "地图坐标导航": {
                            "attach": {
                                "quests": "q变动坐标点0号"
                            }
                        },
                        "关卡选择": {
                            "template": [
                                "map/Fuyuki/熊熊燃烧的森林.png"
                            ]
                        }
                    }
                }
            ]
        }
    }
}