{
    "option": {
        "奥林波斯": {
            "type": "select",
            "label": "关卡",
            "default": "滑翔点",
            "cases": [
                {
                    "name": "滑翔点",
                    "label": "滑翔点",
                    "pipeline_override": {
                        "地图坐标导航": {
                            "attach": {
                                "quests": "q变动坐标点0号"
                            }
                        },
                        "关卡选择": {
                            "template": [
                                "map/Fuyuki/熊熊燃烧的森林.png"
                            ]
                        }
                    }
                },
                {
                    "name": "星间都市西部",
                    "label": "星间都市西部",
                    "pipeline_override": {
                        "地图坐标导航": {
                            "attach": {
                                "quests": "q变动坐标点0号"
                            }
                        },
                        "关卡选择": {
                            "template": [
                                "map/Fuyuki/熊熊燃烧的森林.png"
                            ]
                        }
                    }
                },
                {
                    "name": "星间都市南部",
                    "label": "星间都市南部",
                    "pipeline_override": {
                        "地图坐标导航": {
                            "attach": {
                                "quests": "q变动坐标点0号"
                            }
                        },
                        "关卡选择": {
                            "template": [
                                "map/Fuyuki/熊熊燃烧的森林.png"
                            ]
                        }
                    }
                },
                {
                    "name": "星间都市东部",
                    "label": "星间都市东部",
                    "pipeline_override": {
                        "地图坐标导航": {
                            "attach": {
                                "quests": "q变动坐标点0号"
                            }
                        },
                        "关卡选择": {
                            "template": [
                                "map/Fuyuki/熊熊燃烧的森林.png"
                            ]
                        }
                    }
                },
                {
                    "name": "祭坛街",
                    "label": "祭坛街",
                    "pipeline_override": {
                        "地图坐标导航": {
                            "attach": {
                                "quests": "q变动坐标点0号"
                            }
                        },
                        "关卡选择": {
                            "template": [
                                "map/Fuyuki/熊熊燃烧的森林.png"
                            ]
                        }
                    }
                },
                {
                    "name": "破神同盟基地",
                    "label": "破神同盟基地",
                    "pipeline_override": {
                        "地图坐标导航": {
                            "attach": {
                                "quests": "q变动坐标点0号"
                            }
                        },
                        "关卡选择": {
                            "template": [
                                "map/Fuyuki/熊熊燃烧的森林.png"
                            ]
                        }
                    }
                },
                {
                    "name": "大工房",
                    "label": "大工房",
                    "pipeline_override": {
                        "地图坐标导航": {
                            "attach": {
                                "quests": "q变动坐标点0号"
                            }
                        },
                        "关卡选择": {
                            "template": [
                                "map/Fuyuki/熊熊燃烧的森林.png"
                            ]
                        }
                    }
                },
                {
                    "name": "空中庭园",
                    "label": "空中庭园",
                    "pipeline_override": {
                        "地图坐标导航": {
                            "attach": {
                                "quests": "q变动坐标点0号"
                            }
                        },
                        "关卡选择": {
                            "template": [
                                "map/Fuyuki/熊熊燃烧的森林.png"
                            ]
                        }
                    }
                },
                {
                    "name": "机神回廊",
                    "label": "机神回廊",
                    "pipeline_override": {
                        "地图坐标导航": {
                            "attach": {
                                "quests": "q变动坐标点0号"
                            }
                        },
                        "关卡选择": {
                            "template": [
                                "map/Fuyuki/熊熊燃烧的森林.png"
                            ]
                        }
                    }
                },
                {
                    "name": "大祭坛",
                    "label": "大祭坛",
                    "pipeline_override": {
                        "地图坐标导航": {
                            "attach": {
                                "quests": "q变动坐标点0号"
                            }
                        },
                        "关卡选择": {
                            "template": [
                                "map/Fuyuki/熊熊燃烧的森林.png"
                            ]
                        }
                    }
                },
                {
                    "name": "地下机构带外围",
                    "label": "地下机构带外围",
                    "pipeline_override": {
                        "地图坐标导航": {
                            "attach": {
                                "quests": "q变动坐标点0号"
                            }
                        },
                        "关卡选择": {
                            "template": [
                                "map/Fuyuki/熊熊燃烧的森林.png"
                            ]
                        }
                    }
                }
            ]
        }
    }
}