{
    "option": {
        "新宿": {
            "type": "select",
            "label": "关卡",
            "default": "代代木二丁目",
            "cases": [
                {
                    "name": "代代木二丁目",
                    "label": "代代木二丁目",
                    "pipeline_override": {
                        "地图坐标导航": {
                            "attach": {
                                "quests": "q变动坐标点0号"
                            }
                        },
                        "关卡选择": {
                            "template": [
                                "map/Fuyuki/熊熊燃烧的森林.png"
                            ]
                        }
                    }
                },
                {
                    "name": "国道20号",
                    "label": "国道20号",
                    "pipeline_override": {
                        "地图坐标导航": {
                            "attach": {
                                "quests": "q变动坐标点0号"
                            }
                        },
                        "关卡选择": {
                            "template": [
                                "map/Fuyuki/熊熊燃烧的森林.png"
                            ]
                        }
                    }
                },
                {
                    "name": "新宿站",
                    "label": "新宿站",
                    "pipeline_override": {
                        "地图坐标导航": {
                            "attach": {
                                "quests": "q变动坐标点0号"
                            }
                        },
                        "关卡选择": {
                            "template": [
                                "map/Fuyuki/熊熊燃烧的森林.png"
                            ]
                        }
                    }
                },
                {
                    "name": "新宿四丁目",
                    "label": "新宿四丁目",
                    "pipeline_override": {
                        "地图坐标导航": {
                            "attach": {
                                "quests": "q变动坐标点0号"
                            }
                        },
                        "关卡选择": {
                            "template": [
                                "map/Fuyuki/熊熊燃烧的森林.png"
                            ]
                        }
                    }
                },
                {
                    "name": "歌舞伎町",
                    "label": "歌舞戏町",
                    "pipeline_override": {
                        "地图坐标导航": {
                            "attach": {
                                "quests": "q变动坐标点0号"
                            }
                        },
                        "关卡选择": {
                            "template": [
                                "map/Fuyuki/熊熊燃烧的森林.png"
                            ]
                        }
                    }
                },
                {
                    "name": "枪身塔",
                    "label": "枪身塔",
                    "pipeline_override": {
                        "地图坐标导航": {
                            "attach": {
                                "quests": "q变动坐标点0号"
                            }
                        },
                        "关卡选择": {
                            "template": [
                                "map/Fuyuki/熊熊燃烧的森林.png"
                            ]
                        }
                    }
                },
                {
                    "name": "舞会会场",
                    "label": "舞会会场",
                    "pipeline_override": {
                        "地图坐标导航": {
                            "attach": {
                                "quests": "q变动坐标点0号"
                            }
                        },
                        "关卡选择": {
                            "template": [
                                "map/Fuyuki/熊熊燃烧的森林.png"
                            ]
                        }
                    }
                },
                {
                    "name": "塔顶楼",
                    "label": "塔顶楼",
                    "pipeline_override": {
                        "地图坐标导航": {
                            "attach": {
                                "quests": "q变动坐标点0号"
                            }
                        },
                        "关卡选择": {
                            "template": [
                                "map/Fuyuki/熊熊燃烧的森林.png"
                            ]
                        }
                    }
                },
                {
                    "name": "新宿御苑",
                    "label": "新宿御苑",
                    "pipeline_override": {
                        "地图坐标导航": {
                            "attach": {
                                "quests": "q变动坐标点0号"
                            }
                        },
                        "关卡选择": {
                            "template": [
                                "map/Fuyuki/熊熊燃烧的森林.png"
                            ]
                        }
                    }
                },
                {
                    "name": "新宿二丁目",
                    "label": "新宿二丁目",
                    "pipeline_override": {
                        "地图坐标导航": {
                            "attach": {
                                "quests": "q变动坐标点0号"
                            }
                        },
                        "关卡选择": {
                            "template": [
                                "map/Fuyuki/熊熊燃烧的森林.png"
                            ]
                        }
                    }
                }
            ]
        }
    }
}